{
  "gitSyncId": "66876f1c2c7ef43f2c319204_e16b4478-67e0-47a0-b540-504346bac3c0",
  "unpublishedPage": {
    "isHidden": false,
    "layouts": [
      {
        "dsl": {
          "backgroundColor": "none",
          "bottomRow": 860,
          "canExtend": true,
          "containerStyle": "none",
          "detachFromLayout": true,
          "dynamicBindingPathList": [],
          "dynamicTriggerPathList": [],
          "leftColumn": 0,
          "minHeight": 900,
          "parentColumnSpace": 1,
          "parentRowSpace": 1,
          "rightColumn": 1174,
          "snapColumns": 64,
          "snapRows": 125,
          "topRow": 0,
          "type": "CANVAS_WIDGET",
          "version": 94,
          "widgetId": "0",
          "widgetName": "MainContainer"
        }
      }
    ],
    "name": "Users",
    "slug": "users"
  }
}